mplstadium/__init__.py
mplstadium/stadium2d.py
mplstadium/stadium3d.py
mplstadium/stadium_base.py
mplstadium/utils.py
mplstadium-0.2.0.dist-info/LICENSE.md
mplstadium-0.2.0.dist-info/METADATA
mplstadium-0.2.0.dist-info/WHEEL
mplstadium-0.2.0.dist-info/RECORD
