Metadata-Version: 2.1
Name: mplstadium
Version: 0.2.0
Summary: A python plotting library for visualisation of stadium data
License: MIT
Author: Peter4137
Author-email: peter.robinson4137@gmail.com
Requires-Python: >=3.10,<4.0
Classifier: License :: OSI Approved :: MIT License
Classifier: Programming Language :: Python :: 3
Classifier: Programming Language :: Python :: 3.10
Classifier: Programming Language :: Python :: 3.11
Classifier: Programming Language :: Python :: 3.12
Requires-Dist: matplotlib (>=3.9.2,<4.0.0)
Requires-Dist: numpy (>=2.1.1,<3.0.0)
